encryptor.py
setup.cfg
setup.py
encryptor.egg-info/PKG-INFO
encryptor.egg-info/SOURCES.txt
encryptor.egg-info/dependency_links.txt
encryptor.egg-info/entry_points.txt
encryptor.egg-info/requires.txt
encryptor.egg-info/top_level.txt