Metadata-Version: 1.0
Name: encryptor
Version: 0.3
Summary: AWS File Encryptor
Home-page: https://github.com/jonwils24/encryptor
Author: Jonathan Wilson
Author-email: wilsonwjonathan@gmail.com
License: UNKNOWN
Platform: UNKNOWN
